{
  "version": "5.4.1",
  "flags": {},
  "shapes": [
    {
      "label": "face",
      "points": [
        [
          1289.2307692307693,
          103.53846153846163
        ],
        [
          2686.153846153846,
          1540.4615384615383
        ]
      ],
      "group_id": null,
      "description": "",
      "shape_type": "rectangle",
      "flags": {},
      "mask": null
    },
    {
      "label": "orange_tile",
      "points": [
        [
          1290.7692307692307,
          175.84615384615395
        ],
        [
          1763.076923076923,
          638.923076923077
        ]
      ],
      "group_id": null,
      "description": "",
      "shape_type": "rectangle",
      "flags": {},
      "mask": null
    },
    {
      "label": "orange_tile",
      "points": [
        [
          1735.3846153846152,
          151.2307692307693
        ],
        [
          2207.6923076923076,
          611.2307692307693
        ]
      ],
      "group_id": null,
      "description": "",
      "shape_type": "rectangle",
      "flags": {},
      "mask": null
    },
    {
      "label": "orange_tile",
      "points": [
        [
          2209.230769230769,
          126.61538461538473
        ],
        [
          2695.3846153846152,
          600.4615384615386
        ]
      ],
      "group_id": null,
      "description": "",
      "shape_type": "rectangle",
      "flags": {},
      "mask": null
    },
    {
      "label": "orange_tile",
      "points": [
        [
          1304.6153846153845,
          643.5384615384617
        ],
        [
          1764.6153846153845,
          1100.4615384615383
        ]
      ],
      "group_id": null,
      "description": "",
      "shape_type": "rectangle",
      "flags": {},
      "mask": null
    },
    {
      "label": "orange_tile",
      "points": [
        [
          1741.5384615384614,
          615.8461538461539
        ],
        [
          2223.076923076923,
          1086.6153846153845
        ]
      ],
      "group_id": null,
      "description": "",
      "shape_type": "rectangle",
      "flags": {},
      "mask": null
    },
    {
      "label": "orange_tile",
      "points": [
        [
          2206.153846153846,
          600.4615384615386
        ],
        [
          2704.6153846153843,
          1075.8461538461538
        ]
      ],
      "group_id": null,
      "description": "",
      "shape_type": "rectangle",
      "flags": {},
      "mask": null
    },
    {
      "label": "orange_tile",
      "points": [
        [
          1320.0,
          1092.7692307692307
        ],
        [
          1776.923076923077,
          1535.8461538461538
        ]
      ],
      "group_id": null,
      "description": "",
      "shape_type": "rectangle",
      "flags": {},
      "mask": null
    },
    {
      "label": "orange_tile",
      "points": [
        [
          1756.923076923077,
          1075.8461538461538
        ],
        [
          2229.230769230769,
          1535.8461538461538
        ]
      ],
      "group_id": null,
      "description": "",
      "shape_type": "rectangle",
      "flags": {},
      "mask": null
    },
    {
      "label": "orange_tile",
      "points": [
        [
          2213.846153846154,
          1063.5384615384614
        ],
        [
          2687.6923076923076,
          1534.3076923076924
        ]
      ],
      "group_id": null,
      "description": "",
      "shape_type": "rectangle",
      "flags": {},
      "mask": null
    }
  ],
  "imagePath": "Cube_00016.jpg",
  "imageData": null,
  "imageHeight": 1844,
  "imageWidth": 4000
}