{
  "version": "5.4.1",
  "flags": {},
  "shapes": [
    {
      "label": "face",
      "points": [
        [
          1795.0,
          573.0
        ],
        [
          2473.0,
          1250.0
        ]
      ],
      "group_id": null,
      "description": "",
      "shape_type": "rectangle",
      "flags": {},
      "mask": null
    },
    {
      "label": "red_tile",
      "points": [
        [
          1834.0,
          579.0
        ],
        [
          2051.0,
          805.0
        ]
      ],
      "group_id": null,
      "description": "",
      "shape_type": "rectangle",
      "flags": {},
      "mask": null
    },
    {
      "label": "orange_tile",
      "points": [
        [
          2048.0,
          599.0
        ],
        [
          2267.0,
          816.0
        ]
      ],
      "group_id": null,
      "description": "",
      "shape_type": "rectangle",
      "flags": {},
      "mask": null
    },
    {
      "label": "green_tile",
      "points": [
        [
          2264.0,
          610.0
        ],
        [
          2472.0,
          837.0
        ]
      ],
      "group_id": null,
      "description": "",
      "shape_type": "rectangle",
      "flags": {},
      "mask": null
    },
    {
      "label": "yellow_tile",
      "points": [
        [
          1818.0,
          785.0
        ],
        [
          2038.0,
          1012.0
        ]
      ],
      "group_id": null,
      "description": "",
      "shape_type": "rectangle",
      "flags": {},
      "mask": null
    },
    {
      "label": "green_tile",
      "points": [
        [
          2035.0,
          804.0
        ],
        [
          2246.0,
          1030.0
        ]
      ],
      "group_id": null,
      "description": "",
      "shape_type": "rectangle",
      "flags": {},
      "mask": null
    },
    {
      "label": "orange_tile",
      "points": [
        [
          2242.0,
          816.0
        ],
        [
          2460.0,
          1040.0
        ]
      ],
      "group_id": null,
      "description": "",
      "shape_type": "rectangle",
      "flags": {},
      "mask": null
    },
    {
      "label": "yellow_tile",
      "points": [
        [
          1788.0,
          994.0
        ],
        [
          2016.0,
          1218.0
        ]
      ],
      "group_id": null,
      "description": "",
      "shape_type": "rectangle",
      "flags": {},
      "mask": null
    },
    {
      "label": "green_tile",
      "points": [
        [
          2007.0,
          1015.0
        ],
        [
          2229.0,
          1235.0
        ]
      ],
      "group_id": null,
      "description": "",
      "shape_type": "rectangle",
      "flags": {},
      "mask": null
    },
    {
      "label": "orange_tile",
      "points": [
        [
          2221.0,
          1023.0
        ],
        [
          2439.0,
          1245.0
        ]
      ],
      "group_id": null,
      "description": "",
      "shape_type": "rectangle",
      "flags": {},
      "mask": null
    }
  ],
  "imagePath": "Cube_00020.jpg",
  "imageData": null,
  "imageHeight": 1844,
  "imageWidth": 4000
}