{
  "version": "5.4.1",
  "flags": {},
  "shapes": [
    {
      "label": "face",
      "points": [
        [
          1397.2727272727273,
          445.6363636363637
        ],
        [
          2564.545454545454,
          1607.4545454545453
        ]
      ],
      "group_id": null,
      "description": "",
      "shape_type": "rectangle",
      "flags": {},
      "mask": null
    },
    {
      "label": "white_tile",
      "points": [
        [
          1399.090909090909,
          489.2727272727273
        ],
        [
          1771.8181818181818,
          856.5454545454545
        ]
      ],
      "group_id": null,
      "description": "",
      "shape_type": "rectangle",
      "flags": {},
      "mask": null
    },
    {
      "label": "white_tile",
      "points": [
        [
          1751.8181818181818,
          467.45454545454544
        ],
        [
          2129.9999999999995,
          851.090909090909
        ]
      ],
      "group_id": null,
      "description": "",
      "shape_type": "rectangle",
      "flags": {},
      "mask": null
    },
    {
      "label": "white_tile",
      "points": [
        [
          2133.6363636363635,
          440.1818181818182
        ],
        [
          2524.545454545454,
          823.8181818181818
        ]
      ],
      "group_id": null,
      "description": "",
      "shape_type": "rectangle",
      "flags": {},
      "mask": null
    },
    {
      "label": "white_tile",
      "points": [
        [
          1408.1818181818182,
          858.3636363636363
        ],
        [
          1790.0,
          1240.181818181818
        ]
      ],
      "group_id": null,
      "description": "",
      "shape_type": "rectangle",
      "flags": {},
      "mask": null
    },
    {
      "label": "white_tile",
      "points": [
        [
          1779.090909090909,
          843.8181818181818
        ],
        [
          2166.363636363636,
          1225.6363636363635
        ]
      ],
      "group_id": null,
      "description": "",
      "shape_type": "rectangle",
      "flags": {},
      "mask": null
    },
    {
      "label": "white_tile",
      "points": [
        [
          2155.454545454545,
          818.3636363636363
        ],
        [
          2551.8181818181815,
          1203.8181818181818
        ]
      ],
      "group_id": null,
      "description": "",
      "shape_type": "rectangle",
      "flags": {},
      "mask": null
    },
    {
      "label": "white_tile",
      "points": [
        [
          1440.909090909091,
          1231.090909090909
        ],
        [
          1817.2727272727273,
          1605.6363636363635
        ]
      ],
      "group_id": null,
      "description": "",
      "shape_type": "rectangle",
      "flags": {},
      "mask": null
    },
    {
      "label": "white_tile",
      "points": [
        [
          1799.090909090909,
          1225.6363636363635
        ],
        [
          2200.9090909090905,
          1600.181818181818
        ]
      ],
      "group_id": null,
      "description": "",
      "shape_type": "rectangle",
      "flags": {},
      "mask": null
    },
    {
      "label": "white_tile",
      "points": [
        [
          2164.545454545454,
          1194.7272727272725
        ],
        [
          2564.545454545454,
          1578.3636363636363
        ]
      ],
      "group_id": null,
      "description": "",
      "shape_type": "rectangle",
      "flags": {},
      "mask": null
    }
  ],
  "imagePath": "Cube_00045.jpg",
  "imageData": null,
  "imageHeight": 1844,
  "imageWidth": 4000
}