{
  "version": "5.4.1",
  "flags": {},
  "shapes": [
    {
      "label": "face",
      "points": [
        [
          1850.602409638554,
          433.4457831325302
        ],
        [
          2874.6987951807228,
          1426.2168674698794
        ]
      ],
      "group_id": null,
      "description": "",
      "shape_type": "rectangle",
      "flags": {},
      "mask": null
    },
    {
      "label": "orange_tile",
      "points": [
        [
          1855.4216867469877,
          435.8554216867471
        ],
        [
          2181.9277108433735,
          765.9759036144578
        ]
      ],
      "group_id": null,
      "description": "",
      "shape_type": "rectangle",
      "flags": {},
      "mask": null
    },
    {
      "label": "red_tile",
      "points": [
        [
          2184.33734939759,
          437.06024096385556
        ],
        [
          2532.5301204819275,
          772.0
        ]
      ],
      "group_id": null,
      "description": "",
      "shape_type": "rectangle",
      "flags": {},
      "mask": null
    },
    {
      "label": "orange_tile",
      "points": [
        [
          2521.6867469879517,
          441.8795180722893
        ],
        [
          2875.9036144578313,
          786.4578313253012
        ]
      ],
      "group_id": null,
      "description": "",
      "shape_type": "rectangle",
      "flags": {},
      "mask": null
    },
    {
      "label": "red_tile",
      "points": [
        [
          1855.4216867469877,
          758.7469879518072
        ],
        [
          2177.1084337349394,
          1090.0722891566265
        ]
      ],
      "group_id": null,
      "description": "",
      "shape_type": "rectangle",
      "flags": {},
      "mask": null
    },
    {
      "label": "orange_tile",
      "points": [
        [
          2175.9036144578313,
          768.3855421686748
        ],
        [
          2510.843373493976,
          1100.9156626506024
        ]
      ],
      "group_id": null,
      "description": "",
      "shape_type": "rectangle",
      "flags": {},
      "mask": null
    },
    {
      "label": "red_tile",
      "points": [
        [
          2513.2530120481924,
          773.2048192771084
        ],
        [
          2854.216867469879,
          1122.6024096385543
        ]
      ],
      "group_id": null,
      "description": "",
      "shape_type": "rectangle",
      "flags": {},
      "mask": null
    },
    {
      "label": "orange_tile",
      "points": [
        [
          1856.6265060240962,
          1081.6385542168675
        ],
        [
          2169.879518072289,
          1393.686746987952
        ]
      ],
      "group_id": null,
      "description": "",
      "shape_type": "rectangle",
      "flags": {},
      "mask": null
    },
    {
      "label": "red_tile",
      "points": [
        [
          2163.855421686747,
          1090.0722891566265
        ],
        [
          2498.7951807228915,
          1414.1686746987953
        ]
      ],
      "group_id": null,
      "description": "",
      "shape_type": "rectangle",
      "flags": {},
      "mask": null
    },
    {
      "label": "orange_tile",
      "points": [
        [
          2498.7951807228915,
          1103.3253012048192
        ],
        [
          2837.349397590361,
          1429.8313253012047
        ]
      ],
      "group_id": null,
      "description": "",
      "shape_type": "rectangle",
      "flags": {},
      "mask": null
    }
  ],
  "imagePath": "Cube_00044.jpg",
  "imageData": null,
  "imageHeight": 1844,
  "imageWidth": 4000
}